flatforge/__init__.py
flatforge/__main__.py
flatforge/cli.py
flatforge/config.py
flatforge/cli/__init__.py
flatforge/cli/main.py
flatforge/core/__init__.py
flatforge/core/exceptions.py
flatforge/core/models.py
flatforge/parsers/__init__.py
flatforge/parsers/config_parser.py
flatforge/parsers/file_parser.py
flatforge/processors/__init__.py
flatforge/processors/base.py
flatforge/processors/conversion.py
flatforge/processors/counter.py
flatforge/processors/encoding.py
flatforge/processors/validation.py
flatforge/rules/__init__.py
flatforge/rules/base.py
flatforge/rules/global_rules.py
flatforge/rules/transformation.py
flatforge/rules/validation.py
flatforge/rules/global_rules/__init__.py
flatforge/rules/global_rules/checksum.py
flatforge/rules/global_rules/count.py
flatforge/rules/global_rules/factory.py
flatforge/rules/global_rules/sum.py
flatforge/rules/global_rules/uniqueness.py
flatforge/rules/validation/__init__.py
flatforge/rules/validation/choice.py
flatforge/rules/validation/date.py
flatforge/rules/validation/factory.py
flatforge/rules/validation/guid.py
flatforge/rules/validation/luhn.py
flatforge/rules/validation/numeric.py
flatforge/rules/validation/regex.py
flatforge/rules/validation/required.py
flatforge/rules/validation/string_length.py
flatforge/transformers/__init__.py
flatforge/transformers/base.py
flatforge/transformers/case.py
flatforge/transformers/date.py
flatforge/transformers/date_format.py
flatforge/transformers/guid.py
flatforge/transformers/luhn.py
flatforge/transformers/mask.py
flatforge/transformers/pad.py
flatforge/transformers/replace.py
flatforge/transformers/substring.py
flatforge/transformers/trim.py
flatforge/transformers/value_resolver.py
flatforge/validators/__init__.py
flatforge/validators/config.py
flatforge/validators/domain.py
flatforge/validators/schema.py
flatforge-0.3.4.dist-info/licenses/LICENSE
tests/__init__.py
tests/unit/__init__.py
tests/unit/test_checksum_rule.py
tests/unit/test_checksum_validation.py
tests/unit/test_cli_validate_config.py
flatforge-0.3.4.dist-info/METADATA
flatforge-0.3.4.dist-info/WHEEL
flatforge-0.3.4.dist-info/entry_points.txt
flatforge-0.3.4.dist-info/top_level.txt
flatforge-0.3.4.dist-info/RECORD
