Metadata-Version: 2.4
Name: flatforge
Version: 0.3.4
Summary: A library for validating and transforming flat files
Home-page: https://github.com/akram0zaki/flatforge
Author: Akram Zaki
Author-email: azpythonprojects@gmail.com
Classifier: Programming Language :: Python :: 3
Classifier: License :: OSI Approved :: MIT License
Classifier: Operating System :: OS Independent
Requires-Python: >=3.6
License-File: LICENSE
Requires-Dist: pyyaml>=6.0
Requires-Dist: click>=8.0.0
Requires-Dist: tqdm>=4.64.0
Requires-Dist: jsonschema>=4.0.0
Dynamic: author
Dynamic: author-email
Dynamic: classifier
Dynamic: description
Dynamic: description-content-type
Dynamic: home-page
Dynamic: license-file
Dynamic: requires-dist
Dynamic: requires-python
Dynamic: summary
